neowg/__init__.py
neowg/config.py
neowg/key_pair.py
neowg/utils.py
neowg/wg_client_config.py
neowg/wg_server_config.py
neowg/wg_service.py
neowg-1.5.0.dist-info/LICENSE
neowg-1.5.0.dist-info/METADATA
neowg-1.5.0.dist-info/WHEEL
neowg-1.5.0.dist-info/RECORD
