Metadata-Version: 2.1
Name: neowg
Version: 1.5.0
Summary: Library for working with wireguard configs.
License: GPLv3
Author: NeoTheBestDeveloper
Author-email: neothebestmain@protonmail.com
Requires-Python: >=3.11
Classifier: License :: OSI Approved :: GNU General Public License v3 (GPLv3)
Classifier: License :: Other/Proprietary License
Classifier: Operating System :: POSIX :: Linux
Classifier: Programming Language :: Python :: 3
Classifier: Programming Language :: Python :: 3.11
Classifier: Programming Language :: Python :: 3.12
Classifier: Programming Language :: Python :: 3.13
